resist/__init__.py
resist/py.typed
resist-0.1.0.dist-info/LICENSE
resist-0.1.0.dist-info/WHEEL
resist-0.1.0.dist-info/METADATA
resist-0.1.0.dist-info/RECORD
